[
  {"title":"QQ阅读电子书阅读器CL221一系列电纸书  小说连载 在线追更 自动翻页 黑色","price":699.0,"pice":"../../../static/img/same1.jpg"},
  {"title":"ZIB智班机器人只能对话儿童玩具高科技早教学习机 男女孩陪伴教育","price":858.0,"pice":"../../../static/img/same2.jpg"},
  {"title":"好奇 HUggies 金装成长裤 XL72片  箱装加大号裤型纸尿裤 【12-17kg】 拉拉裤","price":139.0,"pice":"../../../static/img/same3.jpg"},
  {"title":"好奇 HUggies 铂金装 超薄透气 纸尿裤 L96+8片 大号尿不湿 【9-14kg】","price":219.0,"pice":"../../../static/img/same5.jpg"},
  {"title":"汰渍 净白去渍洗衣粉 [柠檬清香] 5kg/袋","price":39.9,"pice":"../../../static/img/same6.jpg"},
  {"title":"gb好孩子 婴儿湿巾  宝宝湿巾  新生儿湿巾  儿童湿纸巾 橄榄滋养卫生屁屁湿巾 80...","price":59.9,"pice":"../../../static/img/same7.jpg"},
  {"title":"海天 生抽酱油 1.9L","price":12.9,"pice":"../../../static/img/same4.jpg"},
  {"title":"罗技 (Logitech) M330 无线静音鼠标 舒适曲线 黑色 M275升级版","price":99.0,"pice":"../../../static/img/same8.jpg"},
  {"title":"金士顿 (Kingston)A400系列 240G SATA3 固态硬盘","price":289.0,"pice":"../../../static/img/same9.jpg"},
  {"title":"双飞燕 (A4TECH) n-810FX 有线鼠标  办公鼠标 USB鼠标 笔记本鼠标 黑色","price":45.0,"pice":"../../../static/img/same10.jpg"},
  {"title":"鹧鸪鸟 (CHUKAR) 700*300mm大鼠标垫 黑色狼头主题","price":19.9,"pice":"../../../static/img/same11.jpg"},
  {"title":"镭拓 (Rantopad) TOTO硅胶手腕妥护腕鼠标垫 深蓝色","price":26.0,"pice":"../../../static/img/same12.jpg"},
  {"title":"江中猴菇 酥性饼干960g (40包) 20天装 猴头菇制成","price":105.0,"pice":"../../../static/img/same13.jpg"}

]
